pytest_with_docker/__init__.py
pytest_with_docker/container_exists.py
pytest_with_docker/defines.py
pytest_with_docker/network_exists.py
pytest_with_docker/es/__init__.py
pytest_with_docker/es/defines.py
pytest_with_docker/es/setup_function.py
pytest_with_docker/es/teardown_function.py
pytest_with_docker-0.0.1.dist-info/LICENSE
pytest_with_docker-0.0.1.dist-info/METADATA
pytest_with_docker-0.0.1.dist-info/WHEEL
pytest_with_docker-0.0.1.dist-info/top_level.txt
pytest_with_docker-0.0.1.dist-info/RECORD
