Metadata-Version: 2.1
Name: pytest-with-docker
Version: 0.0.1
Summary: pytest with docker helpers.
Home-page: https://github.com/kotsutsumi/pytest-with-docker
Author: Kazuhiro Kotsutsumi
License: The MIT License
Platform: UNKNOWN
License-File: LICENSE
Requires-Dist: docker
Requires-Dist: elasticsearch
Requires-Dist: get-port
Requires-Dist: requests
Requires-Dist: pytest
